MANIFEST.in
setup.py
django_indisposable_email_field.egg-info/PKG-INFO
django_indisposable_email_field.egg-info/SOURCES.txt
django_indisposable_email_field.egg-info/dependency_links.txt
django_indisposable_email_field.egg-info/top_level.txt
indisposable_email_field/__init__.py
indisposable_email_field/admin.py
indisposable_email_field/fields.py
indisposable_email_field/models.py
indisposable_email_field/locale/de/LC_MESSAGES/django.mo
indisposable_email_field/locale/de/LC_MESSAGES/django.po
indisposable_email_field/migrations/0001_initial.py
indisposable_email_field/migrations/0002_data.py
indisposable_email_field/migrations/__init__.py