Metadata-Version: 1.1
Name: django-indisposable-email-field
Version: 0.1.5
Summary: A Django form-Field that will check if the given email-address is a Disposable Email Address and block it accordingly.
Home-page: https://github.com/sinnwerkstatt/django-indisposable-email-field
Author: Andreas Nüßlein
Author-email: andreas.nuesslein@sinnwerkstatt.com
License: Apache License 2.0
Platform: UNKNOWN
Classifier: Development Status :: 4 - Beta
Classifier: Intended Audience :: Developers
Classifier: Programming Language :: Python
